{
  "versionCode": 21,
  "versionName": "1.9.2",
  "releaseDate": "2026-06-13",
  "showAsSheet": true,
  "sections": [
    {
      "type": "NEW",
      "bullets": [
        "নতুন “আপনার জন্য” ট্যাব — একটি ব্যক্তিগত আবিষ্কার ফিড, যা আপনার পছন্দ অনুযায়ী সাজানো নতুন রিলিজ ও লুকানো রত্ন তুলে ধরে। এটি ডিফল্টভাবে খোলে, আর আবিষ্কার থাকে এক ট্যাপ দূরে।",
        "আপনার ফিড সম্পূর্ণভাবে আপনার ডিভাইসেই ব্যক্তিগতকৃত হয়, আপনি যেসব রিপোজিটরি স্টার ও ইনস্টল করেন তার ভিত্তিতে। আপনি কী পছন্দ করেন তার কিছুই কখনো আপনার ফোন ছেড়ে যায় না।"
      ]
    }
  ]
}
